terra_proto/__init__.py
terra_proto/alliance/__init__.py
terra_proto/alliance/alliance/__init__.py
terra_proto/amino/__init__.py
terra_proto/cosmos/__init__.py
terra_proto/cosmos/app/__init__.py
terra_proto/cosmos/app/runtime/__init__.py
terra_proto/cosmos/app/runtime/v1alpha1/__init__.py
terra_proto/cosmos/app/v1alpha1/__init__.py
terra_proto/cosmos/auth/__init__.py
terra_proto/cosmos/auth/module/__init__.py
terra_proto/cosmos/auth/module/v1/__init__.py
terra_proto/cosmos/auth/v1beta1/__init__.py
terra_proto/cosmos/authz/__init__.py
terra_proto/cosmos/authz/module/__init__.py
terra_proto/cosmos/authz/module/v1/__init__.py
terra_proto/cosmos/authz/v1beta1/__init__.py
terra_proto/cosmos/autocli/__init__.py
terra_proto/cosmos/autocli/v1/__init__.py
terra_proto/cosmos/bank/__init__.py
terra_proto/cosmos/bank/module/__init__.py
terra_proto/cosmos/bank/module/v1/__init__.py
terra_proto/cosmos/bank/v1beta1/__init__.py
terra_proto/cosmos/base/__init__.py
terra_proto/cosmos/base/abci/__init__.py
terra_proto/cosmos/base/abci/v1beta1/__init__.py
terra_proto/cosmos/base/kv/__init__.py
terra_proto/cosmos/base/kv/v1beta1/__init__.py
terra_proto/cosmos/base/node/__init__.py
terra_proto/cosmos/base/node/v1beta1/__init__.py
terra_proto/cosmos/base/query/__init__.py
terra_proto/cosmos/base/query/v1beta1/__init__.py
terra_proto/cosmos/base/reflection/__init__.py
terra_proto/cosmos/base/reflection/v1beta1/__init__.py
terra_proto/cosmos/base/reflection/v2alpha1/__init__.py
terra_proto/cosmos/base/snapshots/__init__.py
terra_proto/cosmos/base/snapshots/v1beta1/__init__.py
terra_proto/cosmos/base/store/__init__.py
terra_proto/cosmos/base/store/v1beta1/__init__.py
terra_proto/cosmos/base/tendermint/__init__.py
terra_proto/cosmos/base/tendermint/v1beta1/__init__.py
terra_proto/cosmos/base/v1beta1/__init__.py
terra_proto/cosmos/capability/__init__.py
terra_proto/cosmos/capability/module/__init__.py
terra_proto/cosmos/capability/module/v1/__init__.py
terra_classic_proto-4.0.1.dist-info/LICENSE
terra_classic_proto-4.0.1.dist-info/METADATA
terra_classic_proto-4.0.1.dist-info/WHEEL
terra_classic_proto-4.0.1.dist-info/RECORD
