Metadata-Version: 2.1
Name: terra-classic-proto
Version: 4.0.1
Summary: The Python Protobuf implementation for Terra Classic
Home-page: https://github.com/geoffmunn/terra.proto
License: MIT
Keywords: blockchain,terra,terra classic,lunc,crypto,luna classic,osmosis,crypto sdk,blockchain sdk
Author: Geoff Munn
Author-email: geoff@zimoobo.com
Requires-Python: >=3.10,<4.0
Classifier: Intended Audience :: Developers
Classifier: License :: OSI Approved :: MIT License
Classifier: Natural Language :: English
Classifier: Programming Language :: Python :: 3
Classifier: Programming Language :: Python :: 3.10
Classifier: Programming Language :: Python :: 3.11
Classifier: Programming Language :: Python :: 3.12
Classifier: Programming Language :: Python :: 3.7
Classifier: Programming Language :: Python :: 3.8
Classifier: Programming Language :: Python :: 3.9
Requires-Dist: MarkupSafe (==2.1.3)
Requires-Dist: betterproto (==2.0.0b4)
Project-URL: Repository, https://github.com/geoffmunn/terra.proto
